ivycheck_sdk/__init__.py
ivycheck_sdk/evaluations.py
ivycheck_sdk/prompts.py
ivycheck_sdk/sdk.py
ivycheck_sdk/sdkconfiguration.py
ivycheck_sdk/tests.py
ivycheck_sdk/models/__init__.py
ivycheck_sdk/models/complete_streamingop.py
ivycheck_sdk/models/completeop.py
ivycheck_sdk/models/completionresponse.py
ivycheck_sdk/models/create_evaluationop.py
ivycheck_sdk/models/create_test_datasetop.py
ivycheck_sdk/models/create_testcaseop.py
ivycheck_sdk/models/eval.py
ivycheck_sdk/models/evaluateop.py
ivycheck_sdk/models/evaluationdataset.py
ivycheck_sdk/models/get_test_casesop.py
ivycheck_sdk/models/health_check_unsecuredop.py
ivycheck_sdk/models/httpvalidationerror.py
ivycheck_sdk/models/rootop.py
ivycheck_sdk/models/run_testsop.py
ivycheck_sdk/models/sdkerror.py
ivycheck_sdk/models/security.py
ivycheck_sdk/models/testcase.py
ivycheck_sdk/models/testcasecreate.py
ivycheck_sdk/models/testcaseforeval.py
ivycheck_sdk/models/testdatasetreturn.py
ivycheck_sdk/models/validationerror.py
ivycheck_sdk/utils/__init__.py
ivycheck_sdk/utils/retries.py
ivycheck_sdk/utils/utils.py
IvyCheck_SDK-0.2.0.dist-info/LICENSE.md
IvyCheck_SDK-0.2.0.dist-info/METADATA
IvyCheck_SDK-0.2.0.dist-info/WHEEL
IvyCheck_SDK-0.2.0.dist-info/top_level.txt
IvyCheck_SDK-0.2.0.dist-info/RECORD
